libname/Spatial.py
libname/__init__.py
sptlanlpy-0.0.1.dist-info/LICENSE.md
sptlanlpy-0.0.1.dist-info/METADATA
sptlanlpy-0.0.1.dist-info/WHEEL
sptlanlpy-0.0.1.dist-info/top_level.txt
sptlanlpy-0.0.1.dist-info/RECORD
