Metadata-Version: 2.1
Name: sptlanlpy
Version: 0.0.1
Summary: Streamlining Spatial Analyses of Cicular Data Set of Properties
Home-page: UNKNOWN
Author: jbrinkm (Jacob Brinkmann)
Author-email: <jbrinkm@umich.edu>
License: UNKNOWN
Keywords: python,spatial,alalysis,MSCG,stadium,Michigan Sports Consulting Group
Platform: UNKNOWN
Classifier: Development Status :: 4 - Beta
Classifier: Intended Audience :: Other Audience
Classifier: Programming Language :: Python :: 3
Classifier: Operating System :: Unix
Classifier: Operating System :: MacOS :: MacOS X
Classifier: Operating System :: Microsoft :: Windows
Requires-Dist: geopandas
Requires-Dist: geopy
Requires-Dist: haversine
